tarvis/common/asyncio/__init__.py
tarvis/common/cache/local/__init__.py
tarvis/common/config/__init__.py
tarvis/common/environ/__init__.py
tarvis/common/logging/__init__.py
tarvis/common/monitoring/__init__.py
tarvis/common/secrets/__init__.py
tarvis/common/time/__init__.py
tarvis/common/trading/__init__.py
tarvis_common-0.9.14.dist-info/LICENSE.txt
tarvis_common-0.9.14.dist-info/METADATA
tarvis_common-0.9.14.dist-info/WHEEL
tarvis_common-0.9.14.dist-info/top_level.txt
tarvis_common-0.9.14.dist-info/RECORD
