Metadata-Version: 2.1
Name: tarvis-common
Version: 0.9.14
Summary: Tarvis Common Library
Home-page: https://tarvislabs.com/
Author: Tarvis Labs
Author-email: python@tarvislabs.com
License: MIT
Platform: UNKNOWN
Classifier: License :: OSI Approved :: MIT License
Requires-Python: >=3.10
License-File: LICENSE.txt
Requires-Dist: dependency-injector (==4.41.0)
Requires-Dist: google-cloud-secret-manager (==2.16.4)
Requires-Dist: google-cloud-logging (==3.8.0)
Requires-Dist: grpcio (==1.56.2)
Requires-Dist: json5 (==0.9.14)
Requires-Dist: objsize (==0.7.0)
Requires-Dist: opencensus-ext-azure (==1.1.11)
Requires-Dist: pendulum (==2.1.2)
Requires-Dist: python-json-logger (==2.0.7)
Requires-Dist: urllib3 (==2.0.7)
